<?xml version="1.0" encoding="UTF-8"?>

<root>
  <snapshot svn="" id="" date="Tue Jan 23 09:43:18 CET 2007">
    <benchmark>
      <class>
        <method max="216" min="216" avg="216.0" stddev="0.0" conf95="0.0" conf99="0.0" name="myResult">
          <result name="myResult">
            <meter max="88" min="24" avg="54.0" stddev="23.108440016582687" conf95="22.646271216251034" conf99="29.763670741358503" name="myResult" unit="ms" description="ms" class="MilliMeter"/>
            <data><![CDATA[46,58,24,88]]></data>
          </result>
          <result name="myResult">
            <meter max="88" min="24" avg="54.0" stddev="23.108440016582687" conf95="22.646271216251034" conf99="29.763670741358503" name="myResult" unit="ms" description="ms" class="MilliMeter"/>
            <data><![CDATA[46,58,24,88]]></data>
          </result>
        </method>
      </class>
    </benchmark>
  </snapshot>
</root>
